{
  "survival-path": [
    "pathfinder",
    "worldfinder",
    "fighter-path",
    "elemental-path",
    "weapon-drop",
    "nomadic-path",
    "critter-culture",
    "jade-coinage",
    "exalted-stamps",
    "tempest-heartbeat",
    "tempest-defence",
    "moondust-hoarding",
    "abomination-slayer-i",
    "abomination-slayer-ii"
  ],
  "pathfinder": [
    "worldfinder",
    "stop-drop-and-roll",
    "fighter-path",
    "tempest-damage",
    "elemental-path",
    "weapon-drop",
    "elemental-vision",
    "nomadic-path",
    "critter-culture",
    "jade-coinage",
    "moon-of-print",
    "survival-path",
    "tempest-heartbeat",
    "tempest-defence",
    "abomination-slayer-i",
    "abomination-slayer-ii",
    "abomination-slayer-iii"
  ],
  "worldfinder": [
    "pathfinder",
    "stop-drop-and-roll",
    "grumblos-guarantee",
    "fighter-path",
    "tempest-damage",
    "tempest-accuracy",
    "elemental-path",
    "weapon-drop",
    "elemental-vision",
    "stone-drop",
    "stone-failsafe",
    "nomadic-path",
    "survival-path",
    "tempest-heartbeat",
    "abomination-slayer-i",
    "abomination-slayer-ii"
  ],
  "stop-drop-and-roll": [
    "pathfinder",
    "worldfinder",
    "grumblos-guarantee",
    "fighter-path",
    "tempest-damage",
    "tempest-accuracy",
    "tempest-crits",
    "tempest-mega-damage",
    "elemental-path",
    "weapon-drop",
    "elemental-vision",
    "stone-drop",
    "medallion-collection",
    "weapon-improvement",
    "stone-failsafe",
    "abomination-slayer-i",
    "abomination-slayer-ii"
  ],
  "grumblos-guarantee": [
    "worldfinder",
    "stop-drop-and-roll",
    "fighter-path",
    "tempest-damage",
    "tempest-accuracy",
    "tempest-crits",
    "tempest-mega-damage",
    "tempest-rapidshot",
    "stardust-hoarding",
    "elemental-path",
    "weapon-drop",
    "elemental-vision",
    "stone-drop",
    "ring-drop",
    "weapon-improvement",
    "stone-failsafe"
  ],
  "fighter-path": [
    "pathfinder",
    "worldfinder",
    "stop-drop-and-roll",
    "grumblos-guarantee",
    "tempest-damage",
    "tempest-accuracy",
    "multishot",
    "tempest-crits",
    "elemental-path",
    "weapon-drop",
    "elemental-vision",
    "stone-failsafe",
    "nomadic-path",
    "moon-of-print",
    "survival-path",
    "tempest-heartbeat",
    "abomination-slayer-i",
    "abomination-slayer-ii",
    "abomination-slayer-iii",
    "abomination-slayer-iv"
  ],
  "tempest-damage": [
    "pathfinder",
    "worldfinder",
    "stop-drop-and-roll",
    "grumblos-guarantee",
    "fighter-path",
    "tempest-accuracy",
    "multishot",
    "tempest-crits",
    "tempest-mega-damage",
    "tempest-rapidshot",
    "tempest-maxhit",
    "elemental-path",
    "elemental-vision",
    "abomination-slayer-i",
    "abomination-slayer-ii",
    "abomination-slayer-iii",
    "abomination-slayer-iv",
    "abomination-slayer-v"
  ],
  "tempest-accuracy": [
    "worldfinder",
    "stop-drop-and-roll",
    "grumblos-guarantee",
    "fighter-path",
    "tempest-damage",
    "multishot",
    "tempest-crits",
    "tempest-mega-damage",
    "tempest-rapidshot",
    "tempest-bullseye",
    "tempest-maxhit",
    "tempest-one-huuuundred-and-eighty",
    "abomination-slayer-i",
    "abomination-slayer-ii",
    "abomination-slayer-iii",
    "abomination-slayer-iv",
    "abomination-slayer-v",
    "abomination-slayer-vi"
  ],
  "multishot": [
    "fighter-path",
    "tempest-damage",
    "tempest-accuracy",
    "tempest-crits",
    "tempest-mega-damage",
    "tempest-rapidshot",
    "tempest-bullseye",
    "tempest-maxhit",
    "abomination-slayer-i",
    "abomination-slayer-ii",
    "abomination-slayer-iii",
    "abomination-slayer-iv",
    "abomination-slayer-v",
    "abomination-slayer-vi",
    "abomination-slayer-vii",
    "abomination-slayer-viii",
    "abomination-slayer-ix"
  ],
  "tempest-crits": [
    "worldfinder",
    "stop-drop-and-roll",
    "grumblos-guarantee",
    "fighter-path",
    "tempest-damage",
    "tempest-accuracy",
    "multishot",
    "tempest-mega-damage",
    "tempest-rapidshot",
    "tempest-maxhit",
    "stardust-hoarding",
    "tempest-ultra-damage",
    "elemental-path",
    "elemental-vision",
    "abomination-slayer-iii",
    "abomination-slayer-v"
  ],
  "tempest-mega-damage": [
    "worldfinder",
    "stop-drop-and-roll",
    "grumblos-guarantee",
    "fighter-path",
    "tempest-damage",
    "tempest-accuracy",
    "multishot",
    "tempest-crits",
    "tempest-rapidshot",
    "stardust-hoarding",
    "elemental-vision",
    "ring-drop",
    "stone-failsafe"
  ],
  "tempest-rapidshot": [
    "grumblos-guarantee",
    "tempest-damage",
    "tempest-accuracy",
    "multishot",
    "tempest-crits",
    "tempest-mega-damage",
    "tempest-bullseye",
    "tempest-maxhit",
    "stardust-hoarding",
    "tempest-ultra-damage",
    "tempest-one-huuuundred-and-eighty",
    "cooldust-hoarding",
    "mastery-destruction"
  ],
  "tempest-bullseye": [
    "tempest-accuracy",
    "multishot",
    "tempest-crits",
    "tempest-rapidshot",
    "tempest-maxhit",
    "tempest-one-huuuundred-and-eighty",
    "abomination-slayer-ii",
    "abomination-slayer-iii",
    "abomination-slayer-iv",
    "abomination-slayer-v",
    "abomination-slayer-vi",
    "abomination-slayer-vii",
    "abomination-slayer-viii",
    "abomination-slayer-ix",
    "abomination-slayer-x",
    "abomination-slayer-xi"
  ],
  "tempest-maxhit": [
    "tempest-damage",
    "tempest-accuracy",
    "multishot",
    "tempest-crits",
    "tempest-rapidshot",
    "tempest-bullseye",
    "stardust-hoarding",
    "tempest-ultra-damage",
    "tempest-one-huuuundred-and-eighty",
    "abomination-slayer-iii",
    "abomination-slayer-v",
    "abomination-slayer-vi",
    "abomination-slayer-viii",
    "abomination-slayer-ix",
    "abomination-slayer-x"
  ],
  "stardust-hoarding": [
    "grumblos-guarantee",
    "tempest-accuracy",
    "tempest-crits",
    "tempest-mega-damage",
    "tempest-rapidshot",
    "tempest-maxhit",
    "tempest-ultra-damage",
    "cooldust-hoarding"
  ],
  "tempest-ultra-damage": [
    "tempest-accuracy",
    "tempest-crits",
    "tempest-rapidshot",
    "tempest-maxhit",
    "stardust-hoarding",
    "tempest-one-huuuundred-and-eighty",
    "cooldust-hoarding",
    "mastery-destruction",
    "abomination-slayer-x"
  ],
  "tempest-one-huuuundred-and-eighty": [
    "tempest-accuracy",
    "multishot",
    "tempest-rapidshot",
    "tempest-bullseye",
    "tempest-maxhit",
    "tempest-ultra-damage",
    "cooldust-hoarding",
    "mastery-destruction",
    "abomination-slayer-ix",
    "abomination-slayer-x",
    "abomination-slayer-xi"
  ],
  "cooldust-hoarding": [
    "tempest-crits",
    "tempest-mega-damage",
    "tempest-rapidshot",
    "tempest-maxhit",
    "stardust-hoarding",
    "tempest-ultra-damage",
    "tempest-one-huuuundred-and-eighty",
    "mastery-destruction"
  ],
  "mastery-destruction": [
    "tempest-rapidshot",
    "tempest-maxhit",
    "tempest-ultra-damage",
    "tempest-one-huuuundred-and-eighty",
    "cooldust-hoarding"
  ],
  "abomination-slayer-iii": [
    "pathfinder",
    "fighter-path",
    "tempest-damage",
    "tempest-accuracy",
    "multishot",
    "tempest-bullseye",
    "nomadic-path",
    "moon-of-print",
    "talented-masters",
    "atomic-cost-crash",
    "abomination-slayer-i",
    "abomination-slayer-ii",
    "abomination-slayer-iv",
    "abomination-slayer-v",
    "abomination-slayer-vi",
    "abomination-slayer-vii",
    "abomination-slayer-viii"
  ],
  "nomadic-path": [
    "pathfinder",
    "elemental-path",
    "critter-culture",
    "jade-coinage",
    "moon-of-print",
    "exalted-stamps",
    "magnesium-atom",
    "survival-path",
    "tempest-heartbeat",
    "tempest-defence",
    "5-minute-mile",
    "abomination-slayer-i",
    "abomination-slayer-ii",
    "abomination-slayer-iii",
    "abomination-slayer-iv"
  ],
  "elemental-path": [
    "pathfinder",
    "worldfinder",
    "stop-drop-and-roll",
    "fighter-path",
    "tempest-damage",
    "weapon-drop",
    "elemental-vision",
    "stone-drop",
    "medallion-collection",
    "nomadic-path",
    "jade-coinage",
    "survival-path",
    "tempest-heartbeat",
    "moondust-hoarding",
    "abomination-slayer-i"
  ],
  "weapon-drop": [
    "pathfinder",
    "worldfinder",
    "stop-drop-and-roll",
    "grumblos-guarantee",
    "fighter-path",
    "elemental-path",
    "elemental-vision",
    "stone-drop",
    "medallion-collection",
    "elemental-destruction",
    "medallion-magnate",
    "the-luck-factor",
    "stone-failsafe",
    "nomadic-path",
    "survival-path",
    "tempest-heartbeat"
  ],
  "elemental-vision": [
    "pathfinder",
    "worldfinder",
    "stop-drop-and-roll",
    "grumblos-guarantee",
    "fighter-path",
    "tempest-damage",
    "tempest-crits",
    "tempest-mega-damage",
    "elemental-path",
    "weapon-drop",
    "stone-drop",
    "medallion-collection",
    "elemental-destruction",
    "medallion-magnate",
    "weapon-improvement",
    "stone-failsafe",
    "abomination-slayer-i"
  ],
  "stone-drop": [
    "pathfinder",
    "worldfinder",
    "stop-drop-and-roll",
    "grumblos-guarantee",
    "elemental-path",
    "weapon-drop",
    "elemental-vision",
    "medallion-collection",
    "elemental-destruction",
    "medallion-magnate",
    "the-luck-factor",
    "weapon-improvement",
    "top-of-the-mornin",
    "stone-failsafe"
  ],
  "medallion-collection": [
    "stop-drop-and-roll",
    "elemental-path",
    "weapon-drop",
    "elemental-vision",
    "stone-drop",
    "elemental-destruction",
    "medallion-magnate",
    "the-luck-factor",
    "top-of-the-mornin",
    "stone-failsafe"
  ],
  "elemental-destruction": [
    "elemental-path",
    "weapon-drop",
    "elemental-vision",
    "stone-drop",
    "medallion-collection",
    "ring-drop",
    "medallion-magnate",
    "the-luck-factor",
    "weapon-improvement",
    "top-of-the-mornin",
    "stone-failsafe"
  ],
  "ring-drop": [
    "grumblos-guarantee",
    "tempest-mega-damage",
    "stone-drop",
    "elemental-destruction",
    "weapon-improvement",
    "top-of-the-mornin",
    "stone-failsafe"
  ],
  "weapon-improvement": [
    "stop-drop-and-roll",
    "grumblos-guarantee",
    "elemental-vision",
    "stone-drop",
    "medallion-collection",
    "elemental-destruction",
    "ring-drop",
    "the-luck-factor",
    "top-of-the-mornin",
    "stone-failsafe"
  ],
  "the-luck-factor": [
    "weapon-drop",
    "stone-drop",
    "medallion-collection",
    "elemental-destruction",
    "medallion-magnate",
    "weapon-improvement",
    "top-of-the-mornin"
  ],
  "medallion-magnate": [
    "weapon-drop",
    "elemental-vision",
    "stone-drop",
    "medallion-collection",
    "elemental-destruction",
    "the-luck-factor",
    "stone-failsafe",
    "tempest-heartbeat"
  ],
  "stone-failsafe": [
    "worldfinder",
    "stop-drop-and-roll",
    "grumblos-guarantee",
    "fighter-path",
    "tempest-mega-damage",
    "elemental-path",
    "weapon-drop",
    "elemental-vision",
    "stone-drop",
    "medallion-collection",
    "elemental-destruction",
    "ring-drop",
    "medallion-magnate",
    "weapon-improvement",
    "top-of-the-mornin"
  ],
  "top-of-the-mornin": [
    "stone-drop",
    "medallion-collection",
    "elemental-destruction",
    "ring-drop",
    "the-luck-factor",
    "weapon-improvement",
    "stone-failsafe"
  ],
  "critter-culture": [
    "nomadic-path",
    "jade-coinage",
    "moon-of-print",
    "exalted-stamps",
    "moon-of-sneak",
    "magnesium-atom",
    "moon-of-damage",
    "survival-path",
    "tempest-heartbeat",
    "tempest-defence",
    "5-minute-mile"
  ],
  "jade-coinage": [
    "pathfinder",
    "nomadic-path",
    "critter-culture",
    "moon-of-print",
    "exalted-stamps",
    "moon-of-sneak",
    "magnesium-atom",
    "moon-of-damage",
    "talented-masters",
    "survival-path",
    "abomination-slayer-i",
    "abomination-slayer-ii",
    "abomination-slayer-iv"
  ],
  "moon-of-print": [
    "pathfinder",
    "nomadic-path",
    "critter-culture",
    "jade-coinage",
    "exalted-stamps",
    "magnesium-atom",
    "talented-masters",
    "atomic-cost-crash",
    "moon-of-experience",
    "abomination-slayer-i",
    "abomination-slayer-ii",
    "abomination-slayer-iii",
    "abomination-slayer-iv",
    "abomination-slayer-v",
    "abomination-slayer-vi",
    "abomination-slayer-vii"
  ],
  "exalted-stamps": [
    "nomadic-path",
    "critter-culture",
    "jade-coinage",
    "moon-of-print",
    "moon-of-sneak",
    "magnesium-atom",
    "all-knowing-eye",
    "moon-of-damage",
    "talented-masters",
    "opa-opa-opa"
  ],
  "moon-of-sneak": [
    "critter-culture",
    "jade-coinage",
    "exalted-stamps",
    "magnesium-atom",
    "all-knowing-eye",
    "moon-of-damage",
    "atomic-potential",
    "tempest-defence",
    "5-minute-mile",
    "mountains-of-dust"
  ],
  "magnesium-atom": [
    "nomadic-path",
    "critter-culture",
    "jade-coinage",
    "moon-of-print",
    "exalted-stamps",
    "moon-of-sneak",
    "all-knowing-eye",
    "moon-of-damage",
    "talented-masters",
    "opa-opa-opa",
    "atomic-cost-crash",
    "my-talent-is-best-talent",
    "moon-of-experience",
    "monument-homage",
    "pristine-collector"
  ],
  "all-knowing-eye": [
    "exalted-stamps",
    "moon-of-sneak",
    "moon-of-damage",
    "opa-opa-opa",
    "atomic-potential",
    "moon-of-sleep",
    "5-minute-mile"
  ],
  "moon-of-damage": [
    "critter-culture",
    "exalted-stamps",
    "moon-of-sneak",
    "magnesium-atom",
    "all-knowing-eye",
    "opa-opa-opa",
    "atomic-potential",
    "my-talent-is-best-talent",
    "moon-of-experience",
    "monument-homage",
    "moon-of-sleep"
  ],
  "opa-opa-opa": [
    "exalted-stamps",
    "magnesium-atom",
    "all-knowing-eye",
    "moon-of-damage",
    "atomic-potential",
    "my-talent-is-best-talent",
    "moon-of-experience",
    "monument-homage",
    "moon-of-sleep",
    "aluminium-atom"
  ],
  "atomic-potential": [
    "moon-of-sneak",
    "all-knowing-eye",
    "moon-of-damage",
    "opa-opa-opa",
    "my-talent-is-best-talent",
    "monument-homage",
    "moon-of-sleep"
  ],
  "my-talent-is-best-talent": [
    "moon-of-damage",
    "opa-opa-opa",
    "atomic-potential",
    "moon-of-experience",
    "monument-homage",
    "moon-of-sleep",
    "aluminium-atom"
  ],
  "moon-of-experience": [
    "moon-of-print",
    "magnesium-atom",
    "moon-of-damage",
    "talented-masters",
    "opa-opa-opa",
    "atomic-cost-crash",
    "my-talent-is-best-talent",
    "monument-homage",
    "pristine-collector",
    "aluminium-atom"
  ],
  "talented-masters": [
    "jade-coinage",
    "moon-of-print",
    "exalted-stamps",
    "magnesium-atom",
    "moon-of-damage",
    "atomic-cost-crash",
    "moon-of-experience",
    "monument-homage",
    "pristine-collector",
    "abomination-slayer-i",
    "abomination-slayer-ii",
    "abomination-slayer-iv",
    "abomination-slayer-vii"
  ],
  "atomic-cost-crash": [
    "moon-of-print",
    "magnesium-atom",
    "talented-masters",
    "moon-of-experience",
    "pristine-collector",
    "abomination-slayer-iii",
    "abomination-slayer-iv",
    "abomination-slayer-v",
    "abomination-slayer-vi",
    "abomination-slayer-vii",
    "abomination-slayer-xiii",
    "abomination-slayer-xiv"
  ],
  "pristine-collector": [
    "magnesium-atom",
    "talented-masters",
    "opa-opa-opa",
    "atomic-cost-crash",
    "moon-of-experience",
    "monument-homage",
    "aluminium-atom",
    "abomination-slayer-xiv",
    "abomination-slayer-xv"
  ],
  "monument-homage": [
    "magnesium-atom",
    "moon-of-damage",
    "opa-opa-opa",
    "atomic-potential",
    "my-talent-is-best-talent",
    "moon-of-experience",
    "pristine-collector",
    "aluminium-atom"
  ],
  "aluminium-atom": [
    "opa-opa-opa",
    "my-talent-is-best-talent",
    "moon-of-experience",
    "monument-homage",
    "moon-of-sleep",
    "pristine-collector"
  ],
  "moon-of-sleep": [
    "all-knowing-eye",
    "opa-opa-opa",
    "atomic-potential",
    "my-talent-is-best-talent"
  ],
  "5-minute-mile": [
    "nomadic-path",
    "critter-culture",
    "jade-coinage",
    "moon-of-sneak",
    "tempest-defence",
    "moondust-hoarding",
    "solardust-hoarding",
    "mountains-of-dust",
    "spire-of-dust",
    "novadust-discovery"
  ],
  "tempest-defence": [
    "nomadic-path",
    "critter-culture",
    "moon-of-sneak",
    "survival-path",
    "tempest-heartbeat",
    "5-minute-mile",
    "moondust-hoarding",
    "solardust-hoarding",
    "mountains-of-dust",
    "spire-of-dust",
    "novadust-discovery"
  ],
  "tempest-heartbeat": [
    "pathfinder",
    "elemental-path",
    "nomadic-path",
    "critter-culture",
    "survival-path",
    "tempest-defence",
    "5-minute-mile",
    "moondust-hoarding",
    "novadust-discovery",
    "abomination-slayer-i"
  ],
  "moondust-hoarding": [
    "survival-path",
    "tempest-heartbeat",
    "tempest-defence",
    "5-minute-mile",
    "solardust-hoarding",
    "tempest-reach",
    "cant-touch-this",
    "novadust-discovery",
    "knockoff-compass"
  ],
  "solardust-hoarding": [
    "tempest-defence",
    "5-minute-mile",
    "mountains-of-dust",
    "cant-touch-this",
    "spire-of-dust",
    "novadust-discovery",
    "knockoff-compass"
  ],
  "mountains-of-dust": [
    "moon-of-sneak",
    "5-minute-mile",
    "solardust-hoarding",
    "spire-of-dust",
    "novadust-discovery"
  ],
  "spire-of-dust": [
    "5-minute-mile",
    "solardust-hoarding",
    "mountains-of-dust",
    "cant-touch-this",
    "novadust-discovery",
    "knockoff-compass"
  ],
  "cant-touch-this": [
    "solardust-hoarding",
    "spire-of-dust",
    "novadust-discovery",
    "knockoff-compass"
  ],
  "novadust-discovery": [
    "tempest-heartbeat",
    "tempest-defence",
    "5-minute-mile",
    "moondust-hoarding",
    "solardust-hoarding",
    "tempest-reach",
    "mountains-of-dust",
    "cant-touch-this",
    "spire-of-dust",
    "knockoff-compass"
  ],
  "tempest-reach": [
    "moondust-hoarding",
    "solardust-hoarding",
    "novadust-discovery",
    "knockoff-compass"
  ],
  "knockoff-compass": [
    "moondust-hoarding",
    "solardust-hoarding",
    "tempest-reach",
    "cant-touch-this",
    "spire-of-dust",
    "novadust-discovery"
  ],
  "abomination-slayer-i": [
    "pathfinder",
    "worldfinder",
    "stop-drop-and-roll",
    "fighter-path",
    "tempest-damage",
    "multishot",
    "elemental-path",
    "elemental-vision",
    "nomadic-path",
    "critter-culture",
    "jade-coinage",
    "moon-of-print",
    "talented-masters",
    "survival-path",
    "tempest-heartbeat",
    "abomination-slayer-ii",
    "abomination-slayer-iii",
    "abomination-slayer-iv",
    "abomination-slayer-v"
  ],
  "abomination-slayer-ii": [
    "pathfinder",
    "worldfinder",
    "stop-drop-and-roll",
    "fighter-path",
    "tempest-damage",
    "multishot",
    "tempest-bullseye",
    "nomadic-path",
    "jade-coinage",
    "moon-of-print",
    "talented-masters",
    "survival-path",
    "abomination-slayer-i",
    "abomination-slayer-iii",
    "abomination-slayer-iv",
    "abomination-slayer-v",
    "abomination-slayer-vi"
  ],
  "abomination-slayer-iv": [
    "fighter-path",
    "tempest-damage",
    "multishot",
    "tempest-bullseye",
    "nomadic-path",
    "jade-coinage",
    "moon-of-print",
    "talented-masters",
    "atomic-cost-crash",
    "pristine-collector",
    "abomination-slayer-i",
    "abomination-slayer-ii",
    "abomination-slayer-iii",
    "abomination-slayer-v",
    "abomination-slayer-vi",
    "abomination-slayer-vii",
    "abomination-slayer-viii",
    "abomination-slayer-ix"
  ],
  "abomination-slayer-v": [
    "tempest-damage",
    "tempest-accuracy",
    "multishot",
    "tempest-bullseye",
    "moon-of-print",
    "atomic-cost-crash",
    "abomination-slayer-i",
    "abomination-slayer-ii",
    "abomination-slayer-iii",
    "abomination-slayer-iv",
    "abomination-slayer-vi",
    "abomination-slayer-vii",
    "abomination-slayer-viii",
    "abomination-slayer-ix",
    "abomination-slayer-x"
  ],
  "abomination-slayer-vi": [
    "tempest-accuracy",
    "multishot",
    "tempest-bullseye",
    "moon-of-print",
    "talented-masters",
    "atomic-cost-crash",
    "abomination-slayer-ii",
    "abomination-slayer-iii",
    "abomination-slayer-iv",
    "abomination-slayer-v",
    "abomination-slayer-vii",
    "abomination-slayer-viii",
    "abomination-slayer-ix",
    "abomination-slayer-x",
    "abomination-slayer-xi",
    "abomination-slayer-xii",
    "abomination-slayer-xiii"
  ],
  "abomination-slayer-vii": [
    "multishot",
    "tempest-bullseye",
    "moon-of-print",
    "talented-masters",
    "atomic-cost-crash",
    "abomination-slayer-iii",
    "abomination-slayer-iv",
    "abomination-slayer-v",
    "abomination-slayer-vi",
    "abomination-slayer-viii",
    "abomination-slayer-ix",
    "abomination-slayer-xi",
    "abomination-slayer-xii",
    "abomination-slayer-xiii",
    "abomination-slayer-xiv",
    "abomination-slayer-xv"
  ],
  "abomination-slayer-viii": [
    "multishot",
    "tempest-bullseye",
    "tempest-maxhit",
    "atomic-cost-crash",
    "abomination-slayer-iii",
    "abomination-slayer-iv",
    "abomination-slayer-v",
    "abomination-slayer-vi",
    "abomination-slayer-vii",
    "abomination-slayer-ix",
    "abomination-slayer-x",
    "abomination-slayer-xi",
    "abomination-slayer-xii",
    "abomination-slayer-xiii",
    "abomination-slayer-xiv",
    "abomination-slayer-xv"
  ],
  "abomination-slayer-ix": [
    "multishot",
    "tempest-bullseye",
    "tempest-maxhit",
    "tempest-one-huuuundred-and-eighty",
    "abomination-slayer-iv",
    "abomination-slayer-v",
    "abomination-slayer-vi",
    "abomination-slayer-vii",
    "abomination-slayer-viii",
    "abomination-slayer-x",
    "abomination-slayer-xi",
    "abomination-slayer-xii",
    "abomination-slayer-xiii",
    "abomination-slayer-xiv",
    "abomination-slayer-xix",
    "abomination-slayer-xx"
  ],
  "abomination-slayer-x": [
    "tempest-bullseye",
    "tempest-maxhit",
    "tempest-one-huuuundred-and-eighty",
    "abomination-slayer-v",
    "abomination-slayer-vi",
    "abomination-slayer-vii",
    "abomination-slayer-viii",
    "abomination-slayer-ix",
    "abomination-slayer-xi",
    "abomination-slayer-xii",
    "abomination-slayer-xiii",
    "abomination-slayer-xvii",
    "abomination-slayer-xviii",
    "abomination-slayer-xix",
    "abomination-slayer-xx",
    "abomination-slayer-xxi"
  ],
  "abomination-slayer-xi": [
    "tempest-bullseye",
    "tempest-one-huuuundred-and-eighty",
    "abomination-slayer-vi",
    "abomination-slayer-vii",
    "abomination-slayer-viii",
    "abomination-slayer-ix",
    "abomination-slayer-x",
    "abomination-slayer-xii",
    "abomination-slayer-xiii",
    "abomination-slayer-xvi",
    "abomination-slayer-xvii",
    "abomination-slayer-xviii",
    "abomination-slayer-xix",
    "abomination-slayer-xx",
    "abomination-slayer-xxi"
  ],
  "abomination-slayer-xii": [
    "tempest-bullseye",
    "atomic-cost-crash",
    "abomination-slayer-vi",
    "abomination-slayer-vii",
    "abomination-slayer-viii",
    "abomination-slayer-ix",
    "abomination-slayer-x",
    "abomination-slayer-xi",
    "abomination-slayer-xiii",
    "abomination-slayer-xiv",
    "abomination-slayer-xv",
    "abomination-slayer-xvi",
    "abomination-slayer-xvii",
    "abomination-slayer-xviii",
    "abomination-slayer-xix",
    "abomination-slayer-xx"
  ],
  "abomination-slayer-xiii": [
    "atomic-cost-crash",
    "abomination-slayer-vi",
    "abomination-slayer-vii",
    "abomination-slayer-viii",
    "abomination-slayer-ix",
    "abomination-slayer-x",
    "abomination-slayer-xi",
    "abomination-slayer-xii",
    "abomination-slayer-xiv",
    "abomination-slayer-xv",
    "abomination-slayer-xvi",
    "abomination-slayer-xvii",
    "abomination-slayer-xviii",
    "abomination-slayer-xix",
    "abomination-slayer-xxx"
  ],
  "abomination-slayer-xiv": [
    "atomic-cost-crash",
    "pristine-collector",
    "abomination-slayer-vii",
    "abomination-slayer-viii",
    "abomination-slayer-xii",
    "abomination-slayer-xiii",
    "abomination-slayer-xv",
    "abomination-slayer-xvi",
    "abomination-slayer-xvii",
    "abomination-slayer-xviii",
    "abomination-slayer-xxix",
    "abomination-slayer-xxx"
  ],
  "abomination-slayer-xv": [
    "pristine-collector",
    "abomination-slayer-vii",
    "abomination-slayer-viii",
    "abomination-slayer-xii",
    "abomination-slayer-xiii",
    "abomination-slayer-xiv",
    "abomination-slayer-xvi",
    "abomination-slayer-xvii",
    "abomination-slayer-xviii",
    "abomination-slayer-xxviii",
    "abomination-slayer-xxix",
    "abomination-slayer-xxx"
  ],
  "abomination-slayer-xvi": [
    "pristine-collector",
    "abomination-slayer-xii",
    "abomination-slayer-xiii",
    "abomination-slayer-xiv",
    "abomination-slayer-xv",
    "abomination-slayer-xvii",
    "abomination-slayer-xviii",
    "abomination-slayer-xxvii",
    "abomination-slayer-xxviii",
    "abomination-slayer-xxix",
    "abomination-slayer-xxx"
  ],
  "abomination-slayer-xvii": [
    "abomination-slayer-x",
    "abomination-slayer-xi",
    "abomination-slayer-xii",
    "abomination-slayer-xiii",
    "abomination-slayer-xiv",
    "abomination-slayer-xv",
    "abomination-slayer-xvi",
    "abomination-slayer-xviii",
    "abomination-slayer-xix",
    "abomination-slayer-xxvi",
    "abomination-slayer-xxvii",
    "abomination-slayer-xxviii",
    "abomination-slayer-xxix",
    "abomination-slayer-xxx"
  ],
  "abomination-slayer-xviii": [
    "abomination-slayer-x",
    "abomination-slayer-xi",
    "abomination-slayer-xii",
    "abomination-slayer-xiii",
    "abomination-slayer-xiv",
    "abomination-slayer-xv",
    "abomination-slayer-xvi",
    "abomination-slayer-xvii",
    "abomination-slayer-xix",
    "abomination-slayer-xx",
    "abomination-slayer-xxv",
    "abomination-slayer-xxvi",
    "abomination-slayer-xxvii",
    "abomination-slayer-xxviii",
    "abomination-slayer-xxix",
    "abomination-slayer-xxx"
  ],
  "abomination-slayer-xix": [
    "abomination-slayer-ix",
    "abomination-slayer-x",
    "abomination-slayer-xi",
    "abomination-slayer-xii",
    "abomination-slayer-xiii",
    "abomination-slayer-xvii",
    "abomination-slayer-xviii",
    "abomination-slayer-xx",
    "abomination-slayer-xxi",
    "abomination-slayer-xxiv",
    "abomination-slayer-xxv",
    "abomination-slayer-xxvi",
    "abomination-slayer-xxvii",
    "abomination-slayer-xxviii",
    "abomination-slayer-xxix"
  ],
  "abomination-slayer-xx": [
    "abomination-slayer-ix",
    "abomination-slayer-x",
    "abomination-slayer-xi",
    "abomination-slayer-xii",
    "abomination-slayer-xviii",
    "abomination-slayer-xix",
    "abomination-slayer-xxi",
    "abomination-slayer-xxii",
    "abomination-slayer-xxiii",
    "abomination-slayer-xxiv",
    "abomination-slayer-xxv",
    "abomination-slayer-xxvi",
    "abomination-slayer-xxvii",
    "abomination-slayer-xxviii"
  ],
  "abomination-slayer-xxi": [
    "abomination-slayer-ix",
    "abomination-slayer-x",
    "abomination-slayer-xi",
    "abomination-slayer-xix",
    "abomination-slayer-xx",
    "abomination-slayer-xxii",
    "abomination-slayer-xxiii",
    "abomination-slayer-xxiv",
    "abomination-slayer-xxv",
    "abomination-slayer-xxvi",
    "abomination-slayer-xxvii"
  ],
  "abomination-slayer-xxii": [
    "abomination-slayer-xix",
    "abomination-slayer-xx",
    "abomination-slayer-xxi",
    "abomination-slayer-xxiii",
    "abomination-slayer-xxiv",
    "abomination-slayer-xxv",
    "abomination-slayer-xxvi"
  ],
  "abomination-slayer-xxiii": [
    "abomination-slayer-xix",
    "abomination-slayer-xx",
    "abomination-slayer-xxi",
    "abomination-slayer-xxii",
    "abomination-slayer-xxiv",
    "abomination-slayer-xxv",
    "abomination-slayer-xxvi"
  ],
  "abomination-slayer-xxiv": [
    "abomination-slayer-xix",
    "abomination-slayer-xx",
    "abomination-slayer-xxi",
    "abomination-slayer-xxii",
    "abomination-slayer-xxiii",
    "abomination-slayer-xxv",
    "abomination-slayer-xxvi"
  ],
  "abomination-slayer-xxv": [
    "abomination-slayer-xviii",
    "abomination-slayer-xix",
    "abomination-slayer-xx",
    "abomination-slayer-xxi",
    "abomination-slayer-xxii",
    "abomination-slayer-xxiii",
    "abomination-slayer-xxiv",
    "abomination-slayer-xxvi",
    "abomination-slayer-xxvii"
  ],
  "abomination-slayer-xxvi": [
    "abomination-slayer-xiii",
    "abomination-slayer-xvii",
    "abomination-slayer-xviii",
    "abomination-slayer-xix",
    "abomination-slayer-xx",
    "abomination-slayer-xxi",
    "abomination-slayer-xxiv",
    "abomination-slayer-xxv",
    "abomination-slayer-xxvii",
    "abomination-slayer-xxviii"
  ],
  "abomination-slayer-xxvii": [
    "abomination-slayer-xv",
    "abomination-slayer-xvi",
    "abomination-slayer-xvii",
    "abomination-slayer-xviii",
    "abomination-slayer-xix",
    "abomination-slayer-xx",
    "abomination-slayer-xxv",
    "abomination-slayer-xxvi",
    "abomination-slayer-xxviii",
    "abomination-slayer-xxix"
  ],
  "abomination-slayer-xxviii": [
    "abomination-slayer-xv",
    "abomination-slayer-xvi",
    "abomination-slayer-xvii",
    "abomination-slayer-xviii",
    "abomination-slayer-xix",
    "abomination-slayer-xxvi",
    "abomination-slayer-xxvii",
    "abomination-slayer-xxix",
    "abomination-slayer-xxx"
  ],
  "abomination-slayer-xxix": [
    "abomination-slayer-xiv",
    "abomination-slayer-xv",
    "abomination-slayer-xvi",
    "abomination-slayer-xvii",
    "abomination-slayer-xviii",
    "abomination-slayer-xxvii",
    "abomination-slayer-xxviii",
    "abomination-slayer-xxx"
  ],
  "abomination-slayer-xxx": [
    "abomination-slayer-xiii",
    "abomination-slayer-xiv",
    "abomination-slayer-xv",
    "abomination-slayer-xvi",
    "abomination-slayer-xvii",
    "abomination-slayer-xxviii",
    "abomination-slayer-xxix"
  ]
}
